[
  {
    "name": "Chacarita",
    "coords": [
      [
        {
          "lat": -34.5959886570639,
          "lng": -58.4528200492791
        },
        {
          "lat": -34.5978347610252,
          "lng": -58.4554840815948
        },
        {
          "lat": -34.5966774864904,
          "lng": -58.4592753814056
        },
        {
          "lat": -34.5967043067336,
          "lng": -58.4656201094845
        },
        {
          "lat": -34.5925515163591,
          "lng": -58.4643817851099
        },
        {
          "lat": -34.5905930920952,
          "lng": -58.4668281722696
        },
        {
          "lat": -34.5860421891544,
          "lng": -58.4618702043843
        },
        {
          "lat": -34.5855276845223,
          "lng": -58.4603788016938
        },
        {
          "lat": -34.5782946601008,
          "lng": -58.4605276992685
        },
        {
          "lat": -34.579070479135,
          "lng": -58.4553992793144
        },
        {
          "lat": -34.5831918210746,
          "lng": -58.4443997765097
        },
        {
          "lat": -34.5845135514129,
          "lng": -58.4447856534
        },
        {
          "lat": -34.5886677008384,
          "lng": -58.4385357500838
        },
        {
          "lat": -34.5943537370358,
          "lng": -58.4505488949718
        },
        {
          "lat": -34.5959886570639,
          "lng": -58.4528200492791
        }
      ]
    ]
  },
  {
    "name": "Paternal",
    "coords": [
      [
        {
          "lat": -34.5965577078058,
          "lng": -58.4655768128541
        },
        {
          "lat": -34.5966774864904,
          "lng": -58.4592753814056
        },
        {
          "lat": -34.5975900748435,
          "lng": -58.4562363723257
        },
        {
          "lat": -34.6038291328157,
          "lng": -58.4581629096411
        },
        {
          "lat": -34.6043736870838,
          "lng": -58.4589348007685
        },
        {
          "lat": -34.6018603931331,
          "lng": -58.4689122599929
        },
        {
          "lat": -34.6053111422447,
          "lng": -58.4740166366363
        },
        {
          "lat": -34.6008251076105,
          "lng": -58.4774987633725
        },
        {
          "lat": -34.6001995767955,
          "lng": -58.4763923124358
        },
        {
          "lat": -34.5996709502012,
          "lng": -58.4788312666633
        },
        {
          "lat": -34.5913075439713,
          "lng": -58.4757241422155
        },
        {
          "lat": -34.58744531424,
          "lng": -58.4708152687488
        },
        {
          "lat": -34.5924672868431,
          "lng": -58.4644091198271
        },
        {
          "lat": -34.5965577078058,
          "lng": -58.4655768128541
        }
      ]
    ]
  },
  {
    "name": "Villa Crespo",
    "coords": [
      [
        {
          "lat": -34.5978273383243,
          "lng": -58.4237529813037
        },
        {
          "lat": -34.5983289364703,
          "lng": -58.4277732175759
        },
        {
          "lat": -34.5991261910455,
          "lng": -58.4294288790204
        },
        {
          "lat": -34.6021338007058,
          "lng": -58.432240603845
        },
        {
          "lat": -34.6055828639918,
          "lng": -58.4392016360998
        },
        {
          "lat": -34.6076156442747,
          "lng": -58.4462474253216
        },
        {
          "lat": -34.6043736870838,
          "lng": -58.4589348007685
        },
        {
          "lat": -34.6038291328157,
          "lng": -58.4581629096411
        },
        {
          "lat": -34.5975900748435,
          "lng": -58.4562363723257
        },
        {
          "lat": -34.5978347610252,
          "lng": -58.4554840815948
        },
        {
          "lat": -34.5943537370358,
          "lng": -58.4505488949718
        },
        {
          "lat": -34.5886677008384,
          "lng": -58.4385357500838
        },
        {
          "lat": -34.5962105180767,
          "lng": -58.4269502240697
        },
        {
          "lat": -34.5977478956967,
          "lng": -58.4233672222353
        },
        {
          "lat": -34.5978273383243,
          "lng": -58.4237529813037
        }
      ]
    ]
  },
  {
    "name": "Villa del Parque",
    "coords": [
      [
        {
          "lat": -34.6148652395239,
          "lng": -58.4946097568899
        },
        {
          "lat": -34.6143910936437,
          "lng": -58.4955729951466
        },
        {
          "lat": -34.6023785329234,
          "lng": -58.5061676697618
        },
        {
          "lat": -34.5967885277424,
          "lng": -58.4971282395771
        },
        {
          "lat": -34.5977580801127,
          "lng": -58.4834561575031
        },
        {
          "lat": -34.6001995767955,
          "lng": -58.4763923124358
        },
        {
          "lat": -34.6008251076105,
          "lng": -58.4774987633725
        },
        {
          "lat": -34.6053111422447,
          "lng": -58.4740166366363
        },
        {
          "lat": -34.6073597049054,
          "lng": -58.4776184023206
        },
        {
          "lat": -34.6101360573524,
          "lng": -58.4886543020126
        },
        {
          "lat": -34.6148652395239,
          "lng": -58.4946097568899
        }
      ]
    ]
  },
  {
    "name": "Almagro",
    "coords": [
      [
        {
          "lat": -34.6141162515854,
          "lng": -58.4128700313089
        },
        {
          "lat": -34.6206423349386,
          "lng": -58.4125438594995
        },
        {
          "lat": -34.6220745322699,
          "lng": -58.4277953059251
        },
        {
          "lat": -34.6151056808615,
          "lng": -58.4292524794516
        },
        {
          "lat": -34.6154492138688,
          "lng": -58.4300285387507
        },
        {
          "lat": -34.6059413604021,
          "lng": -58.4306691121634
        },
        {
          "lat": -34.6026734568799,
          "lng": -58.4333340897606
        },
        {
          "lat": -34.6021338007058,
          "lng": -58.432240603845
        },
        {
          "lat": -34.5991261910455,
          "lng": -58.4294288790204
        },
        {
          "lat": -34.5979442688696,
          "lng": -58.4267851958388
        },
        {
          "lat": -34.5980030767748,
          "lng": -58.4119188098038
        },
        {
          "lat": -34.607246350613,
          "lng": -58.4139082529045
        },
        {
          "lat": -34.6081900636069,
          "lng": -58.4146599808851
        },
        {
          "lat": -34.6107364191075,
          "lng": -58.4144670312593
        },
        {
          "lat": -34.6141162515854,
          "lng": -58.4128700313089
        }
      ]
    ]
  },
  {
    "name": "Caballito",
    "coords": [
      [
        {
          "lat": -34.6070470885963,
          "lng": -58.4306058283309
        },
        {
          "lat": -34.6154492138688,
          "lng": -58.4300285387507
        },
        {
          "lat": -34.6151056808615,
          "lng": -58.4292524794516
        },
        {
          "lat": -34.6269984842493,
          "lng": -58.4267558142259
        },
        {
          "lat": -34.6306390990819,
          "lng": -58.4515763751329
        },
        {
          "lat": -34.6073730117801,
          "lng": -58.4627046323134
        },
        {
          "lat": -34.604491844775,
          "lng": -58.4584739254559
        },
        {
          "lat": -34.6076156442747,
          "lng": -58.4462474253216
        },
        {
          "lat": -34.6055828639918,
          "lng": -58.4392016360998
        },
        {
          "lat": -34.6026734568799,
          "lng": -58.4333340897606
        },
        {
          "lat": -34.6059413604021,
          "lng": -58.4306691121634
        },
        {
          "lat": -34.6070470885963,
          "lng": -58.4306058283309
        }
      ]
    ]
  },
  {
    "name": "Villa Santa Rita",
    "coords": [
      [
        {
          "lat": -34.6242871724757,
          "lng": -58.4819203599833
        },
        {
          "lat": -34.6246298692564,
          "lng": -58.4827426404615
        },
        {
          "lat": -34.6150160431958,
          "lng": -58.4947856335725
        },
        {
          "lat": -34.6101360573524,
          "lng": -58.4886543020126
        },
        {
          "lat": -34.6081267542887,
          "lng": -58.4804102870483
        },
        {
          "lat": -34.6191552945294,
          "lng": -58.4716211588348
        },
        {
          "lat": -34.6242871724757,
          "lng": -58.4819203599833
        }
      ]
    ]
  },
  {
    "name": "Monte Castro",
    "coords": [
      [
        {
          "lat": -34.6240324216321,
          "lng": -58.5034920611534
        },
        {
          "lat": -34.6275943807029,
          "lng": -58.5072937377628
        },
        {
          "lat": -34.6242786537063,
          "lng": -58.5116515481881
        },
        {
          "lat": -34.628450326008,
          "lng": -58.5163822806213
        },
        {
          "lat": -34.6244050873326,
          "lng": -58.521636691421
        },
        {
          "lat": -34.6167316964764,
          "lng": -58.5130467127704
        },
        {
          "lat": -34.6091257666556,
          "lng": -58.5001924853705
        },
        {
          "lat": -34.6143910936437,
          "lng": -58.4955729951466
        },
        {
          "lat": -34.6167283414358,
          "lng": -58.4926363840486
        },
        {
          "lat": -34.6213705332025,
          "lng": -58.4982008801955
        },
        {
          "lat": -34.6240324216321,
          "lng": -58.5034920611534
        }
      ]
    ]
  },
  {
    "name": "Villa Real",
    "coords": [
      [
        {
          "lat": -34.613999981063,
          "lng": -58.525116079791
        },
        {
          "lat": -34.6202152151591,
          "lng": -58.51695012847
        },
        {
          "lat": -34.6244050873326,
          "lng": -58.521636691421
        },
        {
          "lat": -34.6234862329553,
          "lng": -58.5228320559649
        },
        {
          "lat": -34.6275228005227,
          "lng": -58.5308028789606
        },
        {
          "lat": -34.6154936535585,
          "lng": -58.531518740591
        },
        {
          "lat": -34.6108956395926,
          "lng": -58.5294689967804
        },
        {
          "lat": -34.613999981063,
          "lng": -58.525116079791
        }
      ]
    ]
  },
  {
    "name": "Flores",
    "coords": [
      [
        {
          "lat": -34.6420397134706,
          "lng": -58.4452515823782
        },
        {
          "lat": -34.6428068428585,
          "lng": -58.4442440448718
        },
        {
          "lat": -34.6417777546089,
          "lng": -58.4430779901734
        },
        {
          "lat": -34.6473523797435,
          "lng": -58.4374222950825
        },
        {
          "lat": -34.6462368723605,
          "lng": -58.4349230922177
        },
        {
          "lat": -34.6498743272452,
          "lng": -58.4304298868698
        },
        {
          "lat": -34.6558034890748,
          "lng": -58.4380054918067
        },
        {
          "lat": -34.6511899138583,
          "lng": -58.4433239350118
        },
        {
          "lat": -34.6508230773584,
          "lng": -58.4546362388594
        },
        {
          "lat": -34.6522993458277,
          "lng": -58.4550617780742
        },
        {
          "lat": -34.6568063613378,
          "lng": -58.4604017770485
        },
        {
          "lat": -34.6514682566608,
          "lng": -58.4670336289651
        },
        {
          "lat": -34.6461701975917,
          "lng": -58.462999008231
        },
        {
          "lat": -34.6413968925516,
          "lng": -58.4692423304431
        },
        {
          "lat": -34.6223843057071,
          "lng": -58.4778072341569
        },
        {
          "lat": -34.6175616884276,
          "lng": -58.4686352117012
        },
        {
          "lat": -34.6138856719602,
          "lng": -58.4594483620377
        },
        {
          "lat": -34.6306390990819,
          "lng": -58.4515763751329
        },
        {
          "lat": -34.6315005476642,
          "lng": -58.4543780777636
        },
        {
          "lat": -34.6374669159246,
          "lng": -58.4514410079411
        },
        {
          "lat": -34.6420397134706,
          "lng": -58.4452515823782
        }
      ]
    ]
  },
  {
    "name": "Floresta",
    "coords": [
      [
        {
          "lat": -34.6241108718058,
          "lng": -58.4833907036583
        },
        {
          "lat": -34.6246298692564,
          "lng": -58.4827426404615
        },
        {
          "lat": -34.6223843057071,
          "lng": -58.4778072341569
        },
        {
          "lat": -34.6366552047109,
          "lng": -58.471302914919
        },
        {
          "lat": -34.6373083610103,
          "lng": -58.473492274813
        },
        {
          "lat": -34.6389347067828,
          "lng": -58.4760723304552
        },
        {
          "lat": -34.6213705332025,
          "lng": -58.4982008801955
        },
        {
          "lat": -34.6167283414358,
          "lng": -58.4926363840486
        },
        {
          "lat": -34.6241108718058,
          "lng": -58.4833907036583
        }
      ]
    ]
  },
  {
    "name": "Constitución",
    "coords": [
      [
        {
          "lat": -34.6305149902026,
          "lng": -58.3786300781753
        },
        {
          "lat": -34.6330317470022,
          "lng": -58.3801432818507
        },
        {
          "lat": -34.6330700975028,
          "lng": -58.3812503588454
        },
        {
          "lat": -34.6308451529637,
          "lng": -58.3813327057591
        },
        {
          "lat": -34.6322205656219,
          "lng": -58.3833915276225
        },
        {
          "lat": -34.6341243913884,
          "lng": -58.3903525995973
        },
        {
          "lat": -34.6181592200746,
          "lng": -58.391696989062
        },
        {
          "lat": -34.6174523306285,
          "lng": -58.3773579627707
        },
        {
          "lat": -34.6236005071346,
          "lng": -58.3770652524455
        },
        {
          "lat": -34.6273016183744,
          "lng": -58.3755729030828
        },
        {
          "lat": -34.6293334822524,
          "lng": -58.3790443098809
        },
        {
          "lat": -34.6305149902026,
          "lng": -58.3786300781753
        }
      ]
    ]
  },
  {
    "name": "San Cristóbal",
    "coords": [
      [
        {
          "lat": -34.6215599589853,
          "lng": -58.3915536991875
        },
        {
          "lat": -34.6272530267853,
          "lng": -58.3911698015239
        },
        {
          "lat": -34.6295159878879,
          "lng": -58.4083644787236
        },
        {
          "lat": -34.6303558693605,
          "lng": -58.411779314803
        },
        {
          "lat": -34.6229748135856,
          "lng": -58.4120418689701
        },
        {
          "lat": -34.6206423349386,
          "lng": -58.4125438594995
        },
        {
          "lat": -34.6188402664301,
          "lng": -58.4035128519242
        },
        {
          "lat": -34.6181592200746,
          "lng": -58.391696989062
        },
        {
          "lat": -34.6215599589853,
          "lng": -58.3915536991875
        }
      ]
    ]
  },
  {
    "name": "Boedo",
    "coords": [
      [
        {
          "lat": -34.6206423349386,
          "lng": -58.4125438594995
        },
        {
          "lat": -34.6229748135856,
          "lng": -58.4120418689701
        },
        {
          "lat": -34.6328567590231,
          "lng": -58.41152056161
        },
        {
          "lat": -34.6352375264852,
          "lng": -58.4104885535212
        },
        {
          "lat": -34.638099355027,
          "lng": -58.4112604414934
        },
        {
          "lat": -34.6402003756307,
          "lng": -58.4234918835546
        },
        {
          "lat": -34.6220745322699,
          "lng": -58.4277953059251
        },
        {
          "lat": -34.6206423349386,
          "lng": -58.4125438594995
        }
      ]
    ]
  },
  {
    "name": "Vélez Sársfield",
    "coords": [
      [
        {
          "lat": -34.6314024168004,
          "lng": -58.4855735176658
        },
        {
          "lat": -34.6369942783834,
          "lng": -58.4785455517697
        },
        {
          "lat": -34.6412999736917,
          "lng": -58.4878055974795
        },
        {
          "lat": -34.636963575377,
          "lng": -58.4933197628638
        },
        {
          "lat": -34.6365134006272,
          "lng": -58.4931162121033
        },
        {
          "lat": -34.6366467538286,
          "lng": -58.4937991847717
        },
        {
          "lat": -34.6317765533735,
          "lng": -58.4999773167952
        },
        {
          "lat": -34.6322077868481,
          "lng": -58.5010420985705
        },
        {
          "lat": -34.6275943807029,
          "lng": -58.5072937377628
        },
        {
          "lat": -34.6240324216321,
          "lng": -58.5034920611534
        },
        {
          "lat": -34.6213705332025,
          "lng": -58.4982008801955
        },
        {
          "lat": -34.6314024168004,
          "lng": -58.4855735176658
        }
      ]
    ]
  },
  {
    "name": "Villa Luro",
    "coords": [
      [
        {
          "lat": -34.6318345193872,
          "lng": -58.5015376247954
        },
        {
          "lat": -34.6322077868481,
          "lng": -58.5010420985705
        },
        {
          "lat": -34.6319506893273,
          "lng": -58.4997058881329
        },
        {
          "lat": -34.6366467538286,
          "lng": -58.4937991847717
        },
        {
          "lat": -34.6365134006272,
          "lng": -58.4931162121033
        },
        {
          "lat": -34.636963575377,
          "lng": -58.4933197628638
        },
        {
          "lat": -34.6412999736917,
          "lng": -58.4878055974795
        },
        {
          "lat": -34.6448479591076,
          "lng": -58.4953021850052
        },
        {
          "lat": -34.6434094516649,
          "lng": -58.497137613172
        },
        {
          "lat": -34.6458181705157,
          "lng": -58.5022994907457
        },
        {
          "lat": -34.6400083430956,
          "lng": -58.5098222312771
        },
        {
          "lat": -34.6373709084626,
          "lng": -58.5105096254193
        },
        {
          "lat": -34.6367178847993,
          "lng": -58.5056722645244
        },
        {
          "lat": -34.635812430125,
          "lng": -58.5068193688073
        },
        {
          "lat": -34.634817493545,
          "lng": -58.5106707373973
        },
        {
          "lat": -34.6345994187548,
          "lng": -58.5083883479252
        },
        {
          "lat": -34.628450326008,
          "lng": -58.5163822806213
        },
        {
          "lat": -34.6242786537063,
          "lng": -58.5116515481881
        },
        {
          "lat": -34.6318345193872,
          "lng": -58.5015376247954
        }
      ]
    ]
  },
  {
    "name": "Parque Patricios",
    "coords": [
      [
        {
          "lat": -34.648302987509,
          "lng": -58.4103697298525
        },
        {
          "lat": -34.648582880896,
          "lng": -58.4121005396964
        },
        {
          "lat": -34.6434552111571,
          "lng": -58.4134364486185
        },
        {
          "lat": -34.6357094526213,
          "lng": -58.4105119449969
        },
        {
          "lat": -34.6328567590231,
          "lng": -58.41152056161
        },
        {
          "lat": -34.6303558693605,
          "lng": -58.411779314803
        },
        {
          "lat": -34.6295159878879,
          "lng": -58.4083644787236
        },
        {
          "lat": -34.6272530267853,
          "lng": -58.3911698015239
        },
        {
          "lat": -34.640205502459,
          "lng": -58.3898814798986
        },
        {
          "lat": -34.6408265315406,
          "lng": -58.3914712109694
        },
        {
          "lat": -34.6420862477315,
          "lng": -58.3914001749859
        },
        {
          "lat": -34.6459184553943,
          "lng": -58.4004924229297
        },
        {
          "lat": -34.6463587423835,
          "lng": -58.4003326140345
        },
        {
          "lat": -34.6467310611915,
          "lng": -58.4010837327626
        },
        {
          "lat": -34.648302987509,
          "lng": -58.4103697298525
        }
      ]
    ]
  },
  {
    "name": "Mataderos",
    "coords": [
      [
        {
          "lat": -34.6745050265102,
          "lng": -58.5025197162337
        },
        {
          "lat": -34.6568918088619,
          "lng": -58.5257736298117
        },
        {
          "lat": -34.6434094516649,
          "lng": -58.497137613172
        },
        {
          "lat": -34.6578444571751,
          "lng": -58.4788178144946
        },
        {
          "lat": -34.6624481556404,
          "lng": -58.4859453051063
        },
        {
          "lat": -34.6633484155153,
          "lng": -58.4889524082073
        },
        {
          "lat": -34.6711803517821,
          "lng": -58.497039908648
        },
        {
          "lat": -34.6745050265102,
          "lng": -58.5025197162337
        }
      ]
    ]
  },
  {
    "name": "Villa Lugano",
    "coords": [
      [
        {
          "lat": -34.659025022031,
          "lng": -58.4657134919338
        },
        {
          "lat": -34.6600493899553,
          "lng": -58.4644302838092
        },
        {
          "lat": -34.6636558845097,
          "lng": -58.4684522640303
        },
        {
          "lat": -34.6636094931345,
          "lng": -58.4701944854535
        },
        {
          "lat": -34.6644386444789,
          "lng": -58.4703660376155
        },
        {
          "lat": -34.6688793871641,
          "lng": -58.4647685538527
        },
        {
          "lat": -34.6693885688721,
          "lng": -58.4632267908613
        },
        {
          "lat": -34.6735347876453,
          "lng": -58.4595465354443
        },
        {
          "lat": -34.674382143465,
          "lng": -58.457727133012
        },
        {
          "lat": -34.6800384129116,
          "lng": -58.4506411431689
        },
        {
          "lat": -34.6917921802477,
          "lng": -58.4633960274781
        },
        {
          "lat": -34.6821378656906,
          "lng": -58.4757972583293
        },
        {
          "lat": -34.6889546082405,
          "lng": -58.483355289321
        },
        {
          "lat": -34.6745085923533,
          "lng": -58.5025259133722
        },
        {
          "lat": -34.6711803517821,
          "lng": -58.497039908648
        },
        {
          "lat": -34.6633484155153,
          "lng": -58.4889524082073
        },
        {
          "lat": -34.6624481556404,
          "lng": -58.4859453051063
        },
        {
          "lat": -34.6578444571751,
          "lng": -58.4788178144946
        },
        {
          "lat": -34.6627728024494,
          "lng": -58.4725153175406
        },
        {
          "lat": -34.6584268649248,
          "lng": -58.4705705668529
        },
        {
          "lat": -34.6591053979505,
          "lng": -58.4695559648637
        },
        {
          "lat": -34.6575154679171,
          "lng": -58.4676553033829
        },
        {
          "lat": -34.659025022031,
          "lng": -58.4657134919338
        }
      ]
    ]
  },
  {
    "name": "San Telmo",
    "coords": [
      [
        {
          "lat": -34.6156251471493,
          "lng": -58.3667344665838
        },
        {
          "lat": -34.6239873627789,
          "lng": -58.365785846027
        },
        {
          "lat": -34.6251213720055,
          "lng": -58.363454985638
        },
        {
          "lat": -34.6251954580434,
          "lng": -58.3679712009248
        },
        {
          "lat": -34.6271424047803,
          "lng": -58.3679451333274
        },
        {
          "lat": -34.6294937856849,
          "lng": -58.3706581576618
        },
        {
          "lat": -34.6266471605175,
          "lng": -58.370963660355
        },
        {
          "lat": -34.6267993946018,
          "lng": -58.3745605374647
        },
        {
          "lat": -34.6273016183744,
          "lng": -58.3755729030828
        },
        {
          "lat": -34.6236005071346,
          "lng": -58.3770652524455
        },
        {
          "lat": -34.6162934637292,
          "lng": -58.3774253374129
        },
        {
          "lat": -34.6156251471493,
          "lng": -58.3667344665838
        }
      ]
    ]
  },
  {
    "name": "Saavedra",
    "coords": [
      [
        {
          "lat": -34.5612869279226,
          "lng": -58.4881310699952
        },
        {
          "lat": -34.5626506555011,
          "lng": -58.4909912633507
        },
        {
          "lat": -34.5613016418566,
          "lng": -58.4919301176211
        },
        {
          "lat": -34.5693920775479,
          "lng": -58.508604827106
        },
        {
          "lat": -34.5699971762164,
          "lng": -58.5090406318798
        },
        {
          "lat": -34.5692650785628,
          "lng": -58.5098754818572
        },
        {
          "lat": -34.5494892458445,
          "lng": -58.500551323831
        },
        {
          "lat": -34.5386305921147,
          "lng": -58.4759530989691
        },
        {
          "lat": -34.5489400157911,
          "lng": -58.468189262655
        },
        {
          "lat": -34.5524209338867,
          "lng": -58.4744359204902
        },
        {
          "lat": -34.5535338102215,
          "lng": -58.4735861446691
        },
        {
          "lat": -34.5612869279226,
          "lng": -58.4881310699952
        }
      ]
    ]
  },
  {
    "name": "Coghlan",
    "coords": [
      [
        {
          "lat": -34.5660977127668,
          "lng": -58.4724205132861
        },
        {
          "lat": -34.5668106521891,
          "lng": -58.4745944778956
        },
        {
          "lat": -34.5662186699921,
          "lng": -58.4751236116257
        },
        {
          "lat": -34.5668491475797,
          "lng": -58.4761901850181
        },
        {
          "lat": -34.5639320493153,
          "lng": -58.4790548996063
        },
        {
          "lat": -34.5624996652309,
          "lng": -58.4811577239302
        },
        {
          "lat": -34.5591043168231,
          "lng": -58.4835597040772
        },
        {
          "lat": -34.5535338102215,
          "lng": -58.4735861446691
        },
        {
          "lat": -34.5613151350192,
          "lng": -58.4670371756465
        },
        {
          "lat": -34.5616873807018,
          "lng": -58.4676839219849
        },
        {
          "lat": -34.5621902624702,
          "lng": -58.4664901777516
        },
        {
          "lat": -34.5660977127668,
          "lng": -58.4724205132861
        }
      ]
    ]
  },
  {
    "name": "Villa Urquiza",
    "coords": [
      [
        {
          "lat": -34.5626425900864,
          "lng": -58.4809767085347
        },
        {
          "lat": -34.5639320493153,
          "lng": -58.4790548996063
        },
        {
          "lat": -34.5668491475797,
          "lng": -58.4761901850181
        },
        {
          "lat": -34.5662186699921,
          "lng": -58.4751236116257
        },
        {
          "lat": -34.5668106521891,
          "lng": -58.4745944778956
        },
        {
          "lat": -34.5664355244244,
          "lng": -58.4729884743343
        },
        {
          "lat": -34.5666615316863,
          "lng": -58.4733684642162
        },
        {
          "lat": -34.5729088400037,
          "lng": -58.4680812613894
        },
        {
          "lat": -34.5848182165973,
          "lng": -58.4887935721301
        },
        {
          "lat": -34.5735492524376,
          "lng": -58.5029467489922
        },
        {
          "lat": -34.5699971762164,
          "lng": -58.5090406318798
        },
        {
          "lat": -34.5693920775479,
          "lng": -58.508604827106
        },
        {
          "lat": -34.5613016418566,
          "lng": -58.4919301176211
        },
        {
          "lat": -34.5626506555011,
          "lng": -58.4909912633507
        },
        {
          "lat": -34.5591043168231,
          "lng": -58.4835597040772
        },
        {
          "lat": -34.5626425900864,
          "lng": -58.4809767085347
        }
      ]
    ]
  },
  {
    "name": "Colegiales",
    "coords": [
      [
        {
          "lat": -34.569065630363,
          "lng": -58.4466910921417
        },
        {
          "lat": -34.5721062457974,
          "lng": -58.4407445138848
        },
        {
          "lat": -34.5753643160567,
          "lng": -58.4439716893686
        },
        {
          "lat": -34.5785469344828,
          "lng": -58.4399388685523
        },
        {
          "lat": -34.5831708409276,
          "lng": -58.4444485731026
        },
        {
          "lat": -34.579070479135,
          "lng": -58.4553992793144
        },
        {
          "lat": -34.5782952880515,
          "lng": -58.4602248340306
        },
        {
          "lat": -34.575008412194,
          "lng": -58.4633555464406
        },
        {
          "lat": -34.5695264569663,
          "lng": -58.457709545512
        },
        {
          "lat": -34.5689980502858,
          "lng": -58.457628015889
        },
        {
          "lat": -34.5661082900862,
          "lng": -58.4522874976288
        },
        {
          "lat": -34.569065630363,
          "lng": -58.4466910921417
        }
      ]
    ]
  },
  {
    "name": "Balvanera",
    "coords": [
      [
        {
          "lat": -34.5980030767748,
          "lng": -58.4119188098038
        },
        {
          "lat": -34.5980359654307,
          "lng": -58.4045066845614
        },
        {
          "lat": -34.599369729579,
          "lng": -58.4020082144739
        },
        {
          "lat": -34.5997603196348,
          "lng": -58.3987230001114
        },
        {
          "lat": -34.5996371407189,
          "lng": -58.3929308254775
        },
        {
          "lat": -34.6112799533936,
          "lng": -58.3918065100655
        },
        {
          "lat": -34.6181592200746,
          "lng": -58.391696989062
        },
        {
          "lat": -34.6188402664301,
          "lng": -58.4035128519242
        },
        {
          "lat": -34.6206423349386,
          "lng": -58.4125438594995
        },
        {
          "lat": -34.6141162515854,
          "lng": -58.4128700313089
        },
        {
          "lat": -34.6107364191075,
          "lng": -58.4144670312593
        },
        {
          "lat": -34.6081900636068,
          "lng": -58.4146599808851
        },
        {
          "lat": -34.607246350613,
          "lng": -58.4139082529045
        },
        {
          "lat": -34.5980030767748,
          "lng": -58.4119188098038
        }
      ]
    ]
  },
  {
    "name": "Villa Gral. Mitre",
    "coords": [
      [
        {
          "lat": -34.6190380529955,
          "lng": -58.4713995731534
        },
        {
          "lat": -34.6081267542887,
          "lng": -58.4804102870483
        },
        {
          "lat": -34.6067494069775,
          "lng": -58.4763646858003
        },
        {
          "lat": -34.6018603931331,
          "lng": -58.4689122599929
        },
        {
          "lat": -34.604491844775,
          "lng": -58.4584739254559
        },
        {
          "lat": -34.6073730117801,
          "lng": -58.4627046323134
        },
        {
          "lat": -34.6138856719602,
          "lng": -58.4594483620377
        },
        {
          "lat": -34.6190380529955,
          "lng": -58.4713995731534
        }
      ]
    ]
  },
  {
    "name": "Parque Chas",
    "coords": [
      [
        {
          "lat": -34.58744531424,
          "lng": -58.4708152687488
        },
        {
          "lat": -34.5917235680243,
          "lng": -58.4758890918379
        },
        {
          "lat": -34.5891189838591,
          "lng": -58.4847104372661
        },
        {
          "lat": -34.5848182165973,
          "lng": -58.4887935721301
        },
        {
          "lat": -34.5791249657802,
          "lng": -58.4789880538035
        },
        {
          "lat": -34.5799583110629,
          "lng": -58.4754240986496
        },
        {
          "lat": -34.5817649732474,
          "lng": -58.4735707508275
        },
        {
          "lat": -34.58744531424,
          "lng": -58.4708152687488
        }
      ]
    ]
  },
  {
    "name": "Agronomía",
    "coords": [
      [
        {
          "lat": -34.5951149914833,
          "lng": -58.4771156675186
        },
        {
          "lat": -34.5996709502012,
          "lng": -58.4788312666633
        },
        {
          "lat": -34.5977580801127,
          "lng": -58.4834561575031
        },
        {
          "lat": -34.5968173886491,
          "lng": -58.4971750925229
        },
        {
          "lat": -34.5944501199565,
          "lng": -58.503543766591
        },
        {
          "lat": -34.5943822420751,
          "lng": -58.5030835155438
        },
        {
          "lat": -34.5939535746883,
          "lng": -58.5034718173482
        },
        {
          "lat": -34.5848182165973,
          "lng": -58.4887935721301
        },
        {
          "lat": -34.5891189838591,
          "lng": -58.4847104372661
        },
        {
          "lat": -34.5917235680243,
          "lng": -58.4758890918379
        },
        {
          "lat": -34.5951149914833,
          "lng": -58.4771156675186
        }
      ]
    ]
  },
  {
    "name": "Villa Ortúzar",
    "coords": [
      [
        {
          "lat": -34.5779429557773,
          "lng": -58.4605469510917
        },
        {
          "lat": -34.5782952880515,
          "lng": -58.4602248340306
        },
        {
          "lat": -34.5782946601008,
          "lng": -58.4605276992685
        },
        {
          "lat": -34.5855276845223,
          "lng": -58.4603788016938
        },
        {
          "lat": -34.5860421891544,
          "lng": -58.4618702043843
        },
        {
          "lat": -34.5905930920952,
          "lng": -58.4668281722696
        },
        {
          "lat": -34.5874599535149,
          "lng": -58.4708045599282
        },
        {
          "lat": -34.5817649732474,
          "lng": -58.4735707508275
        },
        {
          "lat": -34.5799583110629,
          "lng": -58.4754240986496
        },
        {
          "lat": -34.5791249657802,
          "lng": -58.4789880538035
        },
        {
          "lat": -34.5724961753266,
          "lng": -58.4673642696436
        },
        {
          "lat": -34.5751051165793,
          "lng": -58.4631871043298
        },
        {
          "lat": -34.5779429557773,
          "lng": -58.4605469510917
        }
      ]
    ]
  },
  {
    "name": "Barracas",
    "coords": [
      [
        {
          "lat": -34.6329258371189,
          "lng": -58.3703353711449
        },
        {
          "lat": -34.6501366170196,
          "lng": -58.3676488363194
        },
        {
          "lat": -34.651334240158,
          "lng": -58.3696567298576
        },
        {
          "lat": -34.652102758711,
          "lng": -58.3700120746499
        },
        {
          "lat": -34.6535787021643,
          "lng": -58.3697869603662
        },
        {
          "lat": -34.6549915394607,
          "lng": -58.3725354484958
        },
        {
          "lat": -34.6568877713594,
          "lng": -58.3740584811186
        },
        {
          "lat": -34.6575903062597,
          "lng": -58.3850550787494
        },
        {
          "lat": -34.6602778478115,
          "lng": -58.3879615941247
        },
        {
          "lat": -34.6611220802904,
          "lng": -58.3905125742793
        },
        {
          "lat": -34.6624167007357,
          "lng": -58.3925392133696
        },
        {
          "lat": -34.6618472972465,
          "lng": -58.3958877706287
        },
        {
          "lat": -34.6620621129766,
          "lng": -58.396988355539
        },
        {
          "lat": -34.6612572545029,
          "lng": -58.3977946679911
        },
        {
          "lat": -34.6607893188678,
          "lng": -58.4004137670655
        },
        {
          "lat": -34.649798275526,
          "lng": -58.4050450004191
        },
        {
          "lat": -34.6470603306162,
          "lng": -58.402745967907
        },
        {
          "lat": -34.6465529340343,
          "lng": -58.400602502211
        },
        {
          "lat": -34.6459184553943,
          "lng": -58.4004924229297
        },
        {
          "lat": -34.6420862477315,
          "lng": -58.3914001749859
        },
        {
          "lat": -34.6408265315406,
          "lng": -58.3914712109694
        },
        {
          "lat": -34.640205502459,
          "lng": -58.3898814798986
        },
        {
          "lat": -34.6341243913884,
          "lng": -58.3903525995973
        },
        {
          "lat": -34.6322205656219,
          "lng": -58.3833915276225
        },
        {
          "lat": -34.6308451529637,
          "lng": -58.3813327057591
        },
        {
          "lat": -34.6330700975028,
          "lng": -58.3812503588454
        },
        {
          "lat": -34.6330317470022,
          "lng": -58.3801432818507
        },
        {
          "lat": -34.6304990043112,
          "lng": -58.3786212324729
        },
        {
          "lat": -34.6293334822524,
          "lng": -58.3790443098809
        },
        {
          "lat": -34.6267993946018,
          "lng": -58.3745605374647
        },
        {
          "lat": -34.6266471605175,
          "lng": -58.370963660355
        },
        {
          "lat": -34.6329258371189,
          "lng": -58.3703353711449
        }
      ]
    ]
  },
  {
    "name": "Parque Avellaneda",
    "coords": [
      [
        {
          "lat": -34.6387869543278,
          "lng": -58.4703750499015
        },
        {
          "lat": -34.6413968925516,
          "lng": -58.4692423304431
        },
        {
          "lat": -34.6461701975917,
          "lng": -58.462999008231
        },
        {
          "lat": -34.6514682566608,
          "lng": -58.4670336289651
        },
        {
          "lat": -34.6568063613378,
          "lng": -58.4604017770485
        },
        {
          "lat": -34.6600493899553,
          "lng": -58.4644302838092
        },
        {
          "lat": -34.6575154679171,
          "lng": -58.4676553033829
        },
        {
          "lat": -34.6591053979505,
          "lng": -58.4695559648637
        },
        {
          "lat": -34.6584268649248,
          "lng": -58.4705705668529
        },
        {
          "lat": -34.6627728024494,
          "lng": -58.4725153175406
        },
        {
          "lat": -34.6448479591076,
          "lng": -58.4953021850052
        },
        {
          "lat": -34.6369942783834,
          "lng": -58.4785455517697
        },
        {
          "lat": -34.6389347067828,
          "lng": -58.4760723304552
        },
        {
          "lat": -34.6373083610103,
          "lng": -58.473492274813
        },
        {
          "lat": -34.6366552047109,
          "lng": -58.471302914919
        },
        {
          "lat": -34.6387869543278,
          "lng": -58.4703750499015
        }
      ]
    ]
  },
  {
    "name": "Parque Chacabuco",
    "coords": [
      [
        {
          "lat": -34.641741258315,
          "lng": -58.4323444043321
        },
        {
          "lat": -34.6451637003841,
          "lng": -58.4321075387748
        },
        {
          "lat": -34.6473523797435,
          "lng": -58.4374222950825
        },
        {
          "lat": -34.6417777546089,
          "lng": -58.4430779901734
        },
        {
          "lat": -34.6428068428585,
          "lng": -58.4442440448718
        },
        {
          "lat": -34.6374669159246,
          "lng": -58.4514410079411
        },
        {
          "lat": -34.6315005476642,
          "lng": -58.4543780777636
        },
        {
          "lat": -34.6306390990819,
          "lng": -58.4515763751329
        },
        {
          "lat": -34.6269984842493,
          "lng": -58.4267558142259
        },
        {
          "lat": -34.6402003756307,
          "lng": -58.4234918835546
        },
        {
          "lat": -34.641741258315,
          "lng": -58.4323444043321
        }
      ]
    ]
  },
  {
    "name": "Nueva Pompeya",
    "coords": [
      [
        {
          "lat": -34.6481348798167,
          "lng": -58.4122089488942
        },
        {
          "lat": -34.648582880896,
          "lng": -58.4121005396964
        },
        {
          "lat": -34.6470603306162,
          "lng": -58.402745967907
        },
        {
          "lat": -34.649798275526,
          "lng": -58.4050450004191
        },
        {
          "lat": -34.6601974970287,
          "lng": -58.4008336801664
        },
        {
          "lat": -34.6594169022206,
          "lng": -58.4026441250986
        },
        {
          "lat": -34.6600953350371,
          "lng": -58.4063687098714
        },
        {
          "lat": -34.6598825342503,
          "lng": -58.4082554512346
        },
        {
          "lat": -34.6589386955184,
          "lng": -58.4101281133804
        },
        {
          "lat": -34.6585129077874,
          "lng": -58.4129625933163
        },
        {
          "lat": -34.6604928140012,
          "lng": -58.4208779380847
        },
        {
          "lat": -34.6620553235193,
          "lng": -58.4240353261196
        },
        {
          "lat": -34.658674118472,
          "lng": -58.426745637652
        },
        {
          "lat": -34.6531131163782,
          "lng": -58.4344334989568
        },
        {
          "lat": -34.6498743272452,
          "lng": -58.4304298868698
        },
        {
          "lat": -34.6462368723605,
          "lng": -58.4349230922177
        },
        {
          "lat": -34.6451637003841,
          "lng": -58.4321075387748
        },
        {
          "lat": -34.641741258315,
          "lng": -58.4323444043321
        },
        {
          "lat": -34.638099355027,
          "lng": -58.4112604414934
        },
        {
          "lat": -34.6434552111571,
          "lng": -58.4134364486185
        },
        {
          "lat": -34.6481348798167,
          "lng": -58.4122089488942
        }
      ]
    ]
  },
  {
    "name": "Palermo",
    "coords": [
      [
        {
          "lat": -34.5520233734028,
          "lng": -58.4267593172764
        },
        {
          "lat": -34.5549000946268,
          "lng": -58.4156792583825
        },
        {
          "lat": -34.5573524531986,
          "lng": -58.4111392583276
        },
        {
          "lat": -34.5565918638971,
          "lng": -58.4095074463204
        },
        {
          "lat": -34.5580718186381,
          "lng": -58.4101770579703
        },
        {
          "lat": -34.5638498191215,
          "lng": -58.404587658582
        },
        {
          "lat": -34.5612399274407,
          "lng": -58.4001349226555
        },
        {
          "lat": -34.5641347976348,
          "lng": -58.4045556753185
        },
        {
          "lat": -34.5648567539683,
          "lng": -58.4040320233536
        },
        {
          "lat": -34.5637157676976,
          "lng": -58.4014012492595
        },
        {
          "lat": -34.5641123480248,
          "lng": -58.399276406517
        },
        {
          "lat": -34.5652271991185,
          "lng": -58.3980385318392
        },
        {
          "lat": -34.5663247899726,
          "lng": -58.3979069492779
        },
        {
          "lat": -34.5690235581029,
          "lng": -58.4002222373443
        },
        {
          "lat": -34.5692236289813,
          "lng": -58.3999621840354
        },
        {
          "lat": -34.5666962272986,
          "lng": -58.3975045112989
        },
        {
          "lat": -34.5666689902995,
          "lng": -58.3969787694811
        },
        {
          "lat": -34.5692288867237,
          "lng": -58.3945617974376
        },
        {
          "lat": -34.5722357271606,
          "lng": -58.3927899180477
        },
        {
          "lat": -34.5721906912083,
          "lng": -58.3952057970513
        },
        {
          "lat": -34.5693489037078,
          "lng": -58.4001266601711
        },
        {
          "lat": -34.5708069482731,
          "lng": -58.3997157523517
        },
        {
          "lat": -34.5741403731302,
          "lng": -58.4026464000829
        },
        {
          "lat": -34.5757367466789,
          "lng": -58.401144552075
        },
        {
          "lat": -34.5785067263343,
          "lng": -58.3965596897453
        },
        {
          "lat": -34.5844718546457,
          "lng": -58.4005436962829
        },
        {
          "lat": -34.5834263897724,
          "lng": -58.4019430855051
        },
        {
          "lat": -34.5834592684237,
          "lng": -58.4061723612826
        },
        {
          "lat": -34.5890571582422,
          "lng": -58.4100810282764
        },
        {
          "lat": -34.5940540688911,
          "lng": -58.4143936419837
        },
        {
          "lat": -34.5978547718645,
          "lng": -58.4160004849245
        },
        {
          "lat": -34.5977478956967,
          "lng": -58.4233672222353
        },
        {
          "lat": -34.5962105180767,
          "lng": -58.4269502240697
        },
        {
          "lat": -34.5845135514129,
          "lng": -58.4447856534
        },
        {
          "lat": -34.5817970365918,
          "lng": -58.4434316752966
        },
        {
          "lat": -34.5785469344828,
          "lng": -58.4399388685523
        },
        {
          "lat": -34.5753643160567,
          "lng": -58.4439716893686
        },
        {
          "lat": -34.5721062457974,
          "lng": -58.4407445138848
        },
        {
          "lat": -34.5678538216449,
          "lng": -58.4490443843996
        },
        {
          "lat": -34.5667128581227,
          "lng": -58.4478544785237
        },
        {
          "lat": -34.5636890745944,
          "lng": -58.4425352483325
        },
        {
          "lat": -34.5621339190165,
          "lng": -58.4411624258167
        },
        {
          "lat": -34.5625777394832,
          "lng": -58.4364272235274
        },
        {
          "lat": -34.5620891843942,
          "lng": -58.4348584761988
        },
        {
          "lat": -34.5616838356982,
          "lng": -58.4382481156204
        },
        {
          "lat": -34.5604199118064,
          "lng": -58.4404892222306
        },
        {
          "lat": -34.5588159151968,
          "lng": -58.441385517031
        },
        {
          "lat": -34.5573030728595,
          "lng": -58.4404428057592
        },
        {
          "lat": -34.5539573025881,
          "lng": -58.4341106260791
        },
        {
          "lat": -34.5535936123733,
          "lng": -58.4346535253175
        },
        {
          "lat": -34.553049939876,
          "lng": -58.4344231019985
        },
        {
          "lat": -34.5511187189825,
          "lng": -58.4309838895436
        },
        {
          "lat": -34.5509501529081,
          "lng": -58.4293982412987
        },
        {
          "lat": -34.5520233734028,
          "lng": -58.4267593172764
        }
      ]
    ]
  },
  {
    "name": "Villa Riachuelo",
    "coords": [
      [
        {
          "lat": -34.6806103119189,
          "lng": -58.4497832682116
        },
        {
          "lat": -34.6849321782368,
          "lng": -58.4442953183736
        },
        {
          "lat": -34.7052931351596,
          "lng": -58.4617154836684
        },
        {
          "lat": -34.6889546082405,
          "lng": -58.483355289321
        },
        {
          "lat": -34.6821378656906,
          "lng": -58.4757972583293
        },
        {
          "lat": -34.6917921802477,
          "lng": -58.4633960274781
        },
        {
          "lat": -34.6805378146004,
          "lng": -58.4511418350466
        },
        {
          "lat": -34.6808637444315,
          "lng": -58.4509657182244
        },
        {
          "lat": -34.6806103119189,
          "lng": -58.4497832682116
        }
      ]
    ]
  },
  {
    "name": "Villa Soldati",
    "coords": [
      [
        {
          "lat": -34.6511657755509,
          "lng": -58.4491320831847
        },
        {
          "lat": -34.6511899138583,
          "lng": -58.4433239350118
        },
        {
          "lat": -34.6558034890748,
          "lng": -58.4380054918067
        },
        {
          "lat": -34.6531131163782,
          "lng": -58.4344334989568
        },
        {
          "lat": -34.658674118472,
          "lng": -58.426745637652
        },
        {
          "lat": -34.6620553235193,
          "lng": -58.4240353261196
        },
        {
          "lat": -34.6648788304442,
          "lng": -58.4273954231565
        },
        {
          "lat": -34.6795769828005,
          "lng": -58.43977349669
        },
        {
          "lat": -34.6801169880939,
          "lng": -58.4416435037358
        },
        {
          "lat": -34.6808891477739,
          "lng": -58.4422746426571
        },
        {
          "lat": -34.6823259827763,
          "lng": -58.442050441068
        },
        {
          "lat": -34.6849321782368,
          "lng": -58.4442953183736
        },
        {
          "lat": -34.6805012403214,
          "lng": -58.4499350307073
        },
        {
          "lat": -34.6808182113935,
          "lng": -58.4510980483008
        },
        {
          "lat": -34.6798384211131,
          "lng": -58.4507757825002
        },
        {
          "lat": -34.674382143465,
          "lng": -58.457727133012
        },
        {
          "lat": -34.6736524631697,
          "lng": -58.4594052824701
        },
        {
          "lat": -34.6693885688721,
          "lng": -58.4632267908613
        },
        {
          "lat": -34.6688793871641,
          "lng": -58.4647685538527
        },
        {
          "lat": -34.6642104057268,
          "lng": -58.4704562527346
        },
        {
          "lat": -34.6636094931345,
          "lng": -58.4701944854535
        },
        {
          "lat": -34.6636558845097,
          "lng": -58.4684522640303
        },
        {
          "lat": -34.6578785467962,
          "lng": -58.461580314615
        },
        {
          "lat": -34.6522993458277,
          "lng": -58.4550617780742
        },
        {
          "lat": -34.6508230773584,
          "lng": -58.4546362388594
        },
        {
          "lat": -34.6511657755509,
          "lng": -58.4491320831847
        }
      ]
    ]
  },
  {
    "name": "Villa Pueyrredon",
    "coords": [
      [
        {
          "lat": -34.5938561595895,
          "lng": -58.5033113250844
        },
        {
          "lat": -34.5817442716468,
          "lng": -58.5145167816089
        },
        {
          "lat": -34.5812681200754,
          "lng": -58.5155362814466
        },
        {
          "lat": -34.5692650785628,
          "lng": -58.5098754818572
        },
        {
          "lat": -34.5735492524376,
          "lng": -58.5029467489922
        },
        {
          "lat": -34.5848182165973,
          "lng": -58.4887935721301
        },
        {
          "lat": -34.5938561595895,
          "lng": -58.5033113250844
        }
      ]
    ]
  },
  {
    "name": "Villa Devoto",
    "coords": [
      [
        {
          "lat": -34.6139197264499,
          "lng": -58.5083084424563
        },
        {
          "lat": -34.6167316964764,
          "lng": -58.5130467127704
        },
        {
          "lat": -34.6202152151591,
          "lng": -58.51695012847
        },
        {
          "lat": -34.6108956395926,
          "lng": -58.5294689967804
        },
        {
          "lat": -34.5812681200754,
          "lng": -58.5155362814466
        },
        {
          "lat": -34.5817442716468,
          "lng": -58.5145167816089
        },
        {
          "lat": -34.5943822420751,
          "lng": -58.5030835155438
        },
        {
          "lat": -34.5944501199565,
          "lng": -58.503543766591
        },
        {
          "lat": -34.5968173886491,
          "lng": -58.4971750925229
        },
        {
          "lat": -34.6023785329234,
          "lng": -58.5061676697618
        },
        {
          "lat": -34.6091257666556,
          "lng": -58.5001924853705
        },
        {
          "lat": -34.6139197264499,
          "lng": -58.5083084424563
        }
      ]
    ]
  },
  {
    "name": "Liniers",
    "coords": [
      [
        {
          "lat": -34.6330100952683,
          "lng": -58.5192540532325
        },
        {
          "lat": -34.6332030845351,
          "lng": -58.5148640537188
        },
        {
          "lat": -34.6355534385852,
          "lng": -58.5088304866027
        },
        {
          "lat": -34.635812430125,
          "lng": -58.5068193688073
        },
        {
          "lat": -34.6367178847993,
          "lng": -58.5056722645244
        },
        {
          "lat": -34.6373709084626,
          "lng": -58.5105096254193
        },
        {
          "lat": -34.6400083430956,
          "lng": -58.5098222312771
        },
        {
          "lat": -34.6458181705157,
          "lng": -58.5022994907457
        },
        {
          "lat": -34.6568918088619,
          "lng": -58.5257736298117
        },
        {
          "lat": -34.6542990415457,
          "lng": -58.5292086646045
        },
        {
          "lat": -34.6347953441841,
          "lng": -58.5303590477146
        },
        {
          "lat": -34.6344707261094,
          "lng": -58.5243003689784
        },
        {
          "lat": -34.633821070473,
          "lng": -58.5206877177954
        },
        {
          "lat": -34.6327972323397,
          "lng": -58.5202409722697
        },
        {
          "lat": -34.6330100952683,
          "lng": -58.5192540532325
        }
      ]
    ]
  },
  {
    "name": "Versalles",
    "coords": [
      [
        {
          "lat": -34.6325601604467,
          "lng": -58.5110429614335
        },
        {
          "lat": -34.6345994187548,
          "lng": -58.5083883479252
        },
        {
          "lat": -34.634817493545,
          "lng": -58.5106707373973
        },
        {
          "lat": -34.6332030845351,
          "lng": -58.5148640537188
        },
        {
          "lat": -34.6327972323397,
          "lng": -58.5202409722697
        },
        {
          "lat": -34.633821070473,
          "lng": -58.5206877177954
        },
        {
          "lat": -34.6347953441841,
          "lng": -58.5303590477146
        },
        {
          "lat": -34.6275228005227,
          "lng": -58.5308028789606
        },
        {
          "lat": -34.6234862329553,
          "lng": -58.5228320559649
        },
        {
          "lat": -34.6325601604467,
          "lng": -58.5110429614335
        }
      ]
    ]
  },
  {
    "name": "Puerto Madero",
    "coords": [
      [
        {
          "lat": -34.5950920711815,
          "lng": -58.3573208786149
        },
        {
          "lat": -34.5966920965277,
          "lng": -58.3534361953991
        },
        {
          "lat": -34.6001089159107,
          "lng": -58.3497310697798
        },
        {
          "lat": -34.6016472442801,
          "lng": -58.3471387718941
        },
        {
          "lat": -34.6067047723038,
          "lng": -58.3458740789696
        },
        {
          "lat": -34.6106638502637,
          "lng": -58.3408606278791
        },
        {
          "lat": -34.6161118369957,
          "lng": -58.3398553797087
        },
        {
          "lat": -34.6169008953935,
          "lng": -58.3407197702892
        },
        {
          "lat": -34.6174546668936,
          "lng": -58.3445845320267
        },
        {
          "lat": -34.6175153364873,
          "lng": -58.3466963811104
        },
        {
          "lat": -34.6168282824533,
          "lng": -58.349065881638
        },
        {
          "lat": -34.6172306364236,
          "lng": -58.3502653438831
        },
        {
          "lat": -34.6181719461161,
          "lng": -58.3508096352105
        },
        {
          "lat": -34.618215836811,
          "lng": -58.3497936303099
        },
        {
          "lat": -34.6187173756407,
          "lng": -58.3499674976681
        },
        {
          "lat": -34.6185517604431,
          "lng": -58.3507221173672
        },
        {
          "lat": -34.6189354180379,
          "lng": -58.3503695487444
        },
        {
          "lat": -34.6191704923281,
          "lng": -58.3506769091041
        },
        {
          "lat": -34.6197709409727,
          "lng": -58.3526924458975
        },
        {
          "lat": -34.619550451567,
          "lng": -58.3551397746524
        },
        {
          "lat": -34.6176387636499,
          "lng": -58.3559976557415
        },
        {
          "lat": -34.6251213720055,
          "lng": -58.363454985638
        },
        {
          "lat": -34.6237947933745,
          "lng": -58.3658398265419
        },
        {
          "lat": -34.6010295674968,
          "lng": -58.3683894892107
        },
        {
          "lat": -34.598321279561,
          "lng": -58.3695123478015
        },
        {
          "lat": -34.5980614176257,
          "lng": -58.3632336427926
        },
        {
          "lat": -34.5971255666786,
          "lng": -58.3634459577139
        },
        {
          "lat": -34.5952442785373,
          "lng": -58.3592514963297
        },
        {
          "lat": -34.5950920711815,
          "lng": -58.3573208786149
        }
      ],
      [
        {
          "lat": -34.5992427530553,
          "lng": -58.366889549473
        },
        {
          "lat": -34.6048810478415,
          "lng": -58.3663397119266
        },
        {
          "lat": -34.6050880712826,
          "lng": -58.3653315426388
        },
        {
          "lat": -34.6047388929561,
          "lng": -58.3646097239569
        },
        {
          "lat": -34.5991592897134,
          "lng": -58.3652462566281
        },
        {
          "lat": -34.5987245857169,
          "lng": -58.366172345001
        },
        {
          "lat": -34.5991858097007,
          "lng": -58.3662759941785
        },
        {
          "lat": -34.5992427530553,
          "lng": -58.366889549473
        }
      ],
      [
        {
          "lat": -34.6055655524033,
          "lng": -58.3661961866141
        },
        {
          "lat": -34.6117326022363,
          "lng": -58.3655597901048
        },
        {
          "lat": -34.6119986979417,
          "lng": -58.3645431430757
        },
        {
          "lat": -34.611594897272,
          "lng": -58.3638161025341
        },
        {
          "lat": -34.6054619440804,
          "lng": -58.3645258574592
        },
        {
          "lat": -34.6051829456324,
          "lng": -58.3653206299855
        },
        {
          "lat": -34.6055655524033,
          "lng": -58.3661961866141
        }
      ],
      [
        {
          "lat": -34.6175927628727,
          "lng": -58.3648597334125
        },
        {
          "lat": -34.617842075347,
          "lng": -58.3638826746576
        },
        {
          "lat": -34.6174427971674,
          "lng": -58.363157784703
        },
        {
          "lat": -34.6123795640349,
          "lng": -58.3637321511725
        },
        {
          "lat": -34.6120937467292,
          "lng": -58.3645341451642
        },
        {
          "lat": -34.6125240345563,
          "lng": -58.3654701196827
        },
        {
          "lat": -34.6175927628727,
          "lng": -58.3648597334125
        }
      ],
      [
        {
          "lat": -34.6234209105258,
          "lng": -58.364228447123
        },
        {
          "lat": -34.6235815284733,
          "lng": -58.3619101309563
        },
        {
          "lat": -34.6231615412484,
          "lng": -58.3625300844071
        },
        {
          "lat": -34.6182138473058,
          "lng": -58.3630726554062
        },
        {
          "lat": -34.6179363706441,
          "lng": -58.3638706525935
        },
        {
          "lat": -34.6183477641447,
          "lng": -58.3648027914107
        },
        {
          "lat": -34.6234209105258,
          "lng": -58.364228447123
        }
      ]
    ]
  },
  {
    "name": "Monserrat",
    "coords": [
      [
        {
          "lat": -34.6068264253902,
          "lng": -58.3687995836552
        },
        {
          "lat": -34.6069011198967,
          "lng": -58.367725984598
        },
        {
          "lat": -34.6156251471493,
          "lng": -58.3667344665838
        },
        {
          "lat": -34.6162934637292,
          "lng": -58.3774253374129
        },
        {
          "lat": -34.6174523306285,
          "lng": -58.3773579627707
        },
        {
          "lat": -34.6181592200746,
          "lng": -58.391696989062
        },
        {
          "lat": -34.6092921487416,
          "lng": -58.3919516385201
        },
        {
          "lat": -34.6078537126088,
          "lng": -58.371252647157
        },
        {
          "lat": -34.6071908383889,
          "lng": -58.3703036593221
        },
        {
          "lat": -34.6065738988467,
          "lng": -58.3701904639348
        },
        {
          "lat": -34.6068264253902,
          "lng": -58.3687995836552
        }
      ]
    ]
  },
  {
    "name": "San Nicolás",
    "coords": [
      [
        {
          "lat": -34.6051742887552,
          "lng": -58.3679211193596
        },
        {
          "lat": -34.6069011198967,
          "lng": -58.367725984598
        },
        {
          "lat": -34.6065738988467,
          "lng": -58.3701904639348
        },
        {
          "lat": -34.6071908383889,
          "lng": -58.3703036593221
        },
        {
          "lat": -34.6078537126088,
          "lng": -58.371252647157
        },
        {
          "lat": -34.6092921487416,
          "lng": -58.3919516385201
        },
        {
          "lat": -34.5996371407189,
          "lng": -58.3929308254775
        },
        {
          "lat": -34.598321279561,
          "lng": -58.3695123478015
        },
        {
          "lat": -34.6010295674968,
          "lng": -58.3683894892107
        },
        {
          "lat": -34.6051742887552,
          "lng": -58.3679211193596
        }
      ]
    ]
  },
  {
    "name": "Belgrano",
    "coords": [
      [
        {
          "lat": -34.5315273335599,
          "lng": -58.4515941108325
        },
        {
          "lat": -34.5325930956192,
          "lng": -58.4507653798336
        },
        {
          "lat": -34.5351420934086,
          "lng": -58.4500084569065
        },
        {
          "lat": -34.5355446244225,
          "lng": -58.4504767383903
        },
        {
          "lat": -34.5357423827814,
          "lng": -58.4531742310643
        },
        {
          "lat": -34.5365176091419,
          "lng": -58.4541198584194
        },
        {
          "lat": -34.5381276022592,
          "lng": -58.4549033007019
        },
        {
          "lat": -34.538805809977,
          "lng": -58.4540880987874
        },
        {
          "lat": -34.539565908556,
          "lng": -58.4521740019821
        },
        {
          "lat": -34.5381422171777,
          "lng": -58.451192419187
        },
        {
          "lat": -34.5373557485288,
          "lng": -58.4498775203901
        },
        {
          "lat": -34.5361334009367,
          "lng": -58.4500173140689
        },
        {
          "lat": -34.5355556416716,
          "lng": -58.4489320916088
        },
        {
          "lat": -34.5363122167407,
          "lng": -58.4493913128475
        },
        {
          "lat": -34.5372203630505,
          "lng": -58.4487116923647
        },
        {
          "lat": -34.537907229861,
          "lng": -58.4492154230073
        },
        {
          "lat": -34.5373369731034,
          "lng": -58.4485940397684
        },
        {
          "lat": -34.5411460351001,
          "lng": -58.4417594820345
        },
        {
          "lat": -34.5387410081019,
          "lng": -58.4442030691445
        },
        {
          "lat": -34.5371204708365,
          "lng": -58.4472920828851
        },
        {
          "lat": -34.5372933435445,
          "lng": -58.4481394334734
        },
        {
          "lat": -34.5360837550318,
          "lng": -58.4464264767624
        },
        {
          "lat": -34.5366066924513,
          "lng": -58.4433623040897
        },
        {
          "lat": -34.5380495231334,
          "lng": -58.441642620082
        },
        {
          "lat": -34.5402953388827,
          "lng": -58.4407393733525
        },
        {
          "lat": -34.5397108982919,
          "lng": -58.4402851190115
        },
        {
          "lat": -34.5403052733857,
          "lng": -58.4394989504609
        },
        {
          "lat": -34.5399482887463,
          "lng": -58.4371946245777
        },
        {
          "lat": -34.5407516707531,
          "lng": -58.4357714050735
        },
        {
          "lat": -34.5425208532995,
          "lng": -58.4350490310699
        },
        {
          "lat": -34.5439813000046,
          "lng": -58.4318749367974
        },
        {
          "lat": -34.545541133017,
          "lng": -58.4307899047318
        },
        {
          "lat": -34.5471140255196,
          "lng": -58.4305679993941
        },
        {
          "lat": -34.5467344915757,
          "lng": -58.4299548877725
        },
        {
          "lat": -34.5471158410449,
          "lng": -58.4297026920272
        },
        {
          "lat": -34.5477484478431,
          "lng": -58.4299782018785
        },
        {
          "lat": -34.5473327598746,
          "lng": -58.4304791695436
        },
        {
          "lat": -34.5477857384084,
          "lng": -58.4306349747428
        },
        {
          "lat": -34.5491066792459,
          "lng": -58.4293436339992
        },
        {
          "lat": -34.549093713456,
          "lng": -58.4278421677571
        },
        {
          "lat": -34.5497900037705,
          "lng": -58.4272941776888
        },
        {
          "lat": -34.5495320546558,
          "lng": -58.4260778174679
        },
        {
          "lat": -34.5500614231903,
          "lng": -58.4256740143058
        },
        {
          "lat": -34.5520237796411,
          "lng": -58.4267582450064
        },
        {
          "lat": -34.5509501529081,
          "lng": -58.4293982412987
        },
        {
          "lat": -34.5514141841313,
          "lng": -58.4316803336417
        },
        {
          "lat": -34.553049939876,
          "lng": -58.4344231019985
        },
        {
          "lat": -34.5535936123733,
          "lng": -58.4346535253175
        },
        {
          "lat": -34.5539573025881,
          "lng": -58.4341106260791
        },
        {
          "lat": -34.5578963092245,
          "lng": -58.4410585303095
        },
        {
          "lat": -34.5588159151968,
          "lng": -58.441385517031
        },
        {
          "lat": -34.5605558749164,
          "lng": -58.4403278682893
        },
        {
          "lat": -34.561756813506,
          "lng": -58.437980191745
        },
        {
          "lat": -34.5617922220649,
          "lng": -58.4349578351151
        },
        {
          "lat": -34.5625370350985,
          "lng": -58.435402445693
        },
        {
          "lat": -34.5621339190165,
          "lng": -58.4411624258167
        },
        {
          "lat": -34.5636890745944,
          "lng": -58.4425352483325
        },
        {
          "lat": -34.5667128581227,
          "lng": -58.4478544785237
        },
        {
          "lat": -34.5678538216449,
          "lng": -58.4490443843996
        },
        {
          "lat": -34.5661082900862,
          "lng": -58.4522874976288
        },
        {
          "lat": -34.5689980502858,
          "lng": -58.457628015889
        },
        {
          "lat": -34.5695264569663,
          "lng": -58.457709545512
        },
        {
          "lat": -34.575008412194,
          "lng": -58.4633555464406
        },
        {
          "lat": -34.5724961753266,
          "lng": -58.4673642696436
        },
        {
          "lat": -34.5729088400037,
          "lng": -58.4680812613894
        },
        {
          "lat": -34.5666615316863,
          "lng": -58.4733684642162
        },
        {
          "lat": -34.5621902624702,
          "lng": -58.4664901777516
        },
        {
          "lat": -34.5616873807018,
          "lng": -58.4676839219849
        },
        {
          "lat": -34.5613151350192,
          "lng": -58.4670371756465
        },
        {
          "lat": -34.558928524183,
          "lng": -58.4691841950682
        },
        {
          "lat": -34.5505040530708,
          "lng": -58.4530063043606
        },
        {
          "lat": -34.5489847697112,
          "lng": -58.4541211632346
        },
        {
          "lat": -34.5426523436413,
          "lng": -58.4492746382907
        },
        {
          "lat": -34.5377987902741,
          "lng": -58.4594426423642
        },
        {
          "lat": -34.5349224254094,
          "lng": -58.4536399740443
        },
        {
          "lat": -34.534316876145,
          "lng": -58.4536611992374
        },
        {
          "lat": -34.5315273335599,
          "lng": -58.4515941108325
        }
      ]
    ]
  },
  {
    "name": "Recoleta",
    "coords": [
      [
        {
          "lat": -34.5721906912083,
          "lng": -58.3952057970513
        },
        {
          "lat": -34.5722357271606,
          "lng": -58.3927899180477
        },
        {
          "lat": -34.5764929152422,
          "lng": -58.3849625800299
        },
        {
          "lat": -34.5764047832219,
          "lng": -58.3834148558284
        },
        {
          "lat": -34.5754475051314,
          "lng": -58.3829708523445
        },
        {
          "lat": -34.5706434547979,
          "lng": -58.3913016196442
        },
        {
          "lat": -34.5700713973828,
          "lng": -58.3910447763775
        },
        {
          "lat": -34.5709430587355,
          "lng": -58.3877597714167
        },
        {
          "lat": -34.5704305745227,
          "lng": -58.380875423003
        },
        {
          "lat": -34.5706559223835,
          "lng": -58.3813563707824
        },
        {
          "lat": -34.570988048405,
          "lng": -58.3807573370336
        },
        {
          "lat": -34.5704141038936,
          "lng": -58.3806145117896
        },
        {
          "lat": -34.5703246758169,
          "lng": -58.3788675715961
        },
        {
          "lat": -34.5720659236704,
          "lng": -58.3757078555864
        },
        {
          "lat": -34.5729072647716,
          "lng": -58.3754050197075
        },
        {
          "lat": -34.5729581668738,
          "lng": -58.3743539465971
        },
        {
          "lat": -34.5747396492448,
          "lng": -58.3712169695293
        },
        {
          "lat": -34.5755546764402,
          "lng": -58.3708710504125
        },
        {
          "lat": -34.5747978447701,
          "lng": -58.3712963234646
        },
        {
          "lat": -34.5730429247224,
          "lng": -58.3743717046191
        },
        {
          "lat": -34.5729973584441,
          "lng": -58.3755001556176
        },
        {
          "lat": -34.572071731433,
          "lng": -58.3758543444098
        },
        {
          "lat": -34.5703917171694,
          "lng": -58.3789513782266
        },
        {
          "lat": -34.5704862785351,
          "lng": -58.3805157917672
        },
        {
          "lat": -34.5710195948898,
          "lng": -58.3807095259796
        },
        {
          "lat": -34.5722963274373,
          "lng": -58.3783124676678
        },
        {
          "lat": -34.572747684994,
          "lng": -58.3782870792231
        },
        {
          "lat": -34.5734117181581,
          "lng": -58.3835805950943
        },
        {
          "lat": -34.574410258481,
          "lng": -58.381811661111
        },
        {
          "lat": -34.5739252274169,
          "lng": -58.3754384929476
        },
        {
          "lat": -34.5766005819584,
          "lng": -58.3707560013641
        },
        {
          "lat": -34.577023795171,
          "lng": -58.3706956893502
        },
        {
          "lat": -34.5775452603952,
          "lng": -58.3767109137284
        },
        {
          "lat": -34.5791023036155,
          "lng": -58.3739717230009
        },
        {
          "lat": -34.5805200713283,
          "lng": -58.3751214877465
        },
        {
          "lat": -34.5799504792293,
          "lng": -58.3761600512028
        },
        {
          "lat": -34.5801619115881,
          "lng": -58.3798362674721
        },
        {
          "lat": -34.5782352961729,
          "lng": -58.3835712371255
        },
        {
          "lat": -34.5782016523951,
          "lng": -58.389864551892
        },
        {
          "lat": -34.5808309894752,
          "lng": -58.3916446426145
        },
        {
          "lat": -34.5835513995301,
          "lng": -58.3869635729226
        },
        {
          "lat": -34.5875003435414,
          "lng": -58.3836858955457
        },
        {
          "lat": -34.5916482473693,
          "lng": -58.3879499543075
        },
        {
          "lat": -34.5992928735805,
          "lng": -58.3868634379837
        },
        {
          "lat": -34.5997603196348,
          "lng": -58.3987230001114
        },
        {
          "lat": -34.599369729579,
          "lng": -58.4020082144739
        },
        {
          "lat": -34.5980359654307,
          "lng": -58.4045066845614
        },
        {
          "lat": -34.5978547718644,
          "lng": -58.4160004849245
        },
        {
          "lat": -34.5940540688911,
          "lng": -58.4143936419837
        },
        {
          "lat": -34.5890571582422,
          "lng": -58.4100810282764
        },
        {
          "lat": -34.5834592684237,
          "lng": -58.4061723612826
        },
        {
          "lat": -34.5834263897724,
          "lng": -58.4019430855051
        },
        {
          "lat": -34.5844718546457,
          "lng": -58.4005436962829
        },
        {
          "lat": -34.5785067263343,
          "lng": -58.3965596897453
        },
        {
          "lat": -34.5757367466789,
          "lng": -58.401144552075
        },
        {
          "lat": -34.5741403731302,
          "lng": -58.4026464000829
        },
        {
          "lat": -34.5708069482731,
          "lng": -58.3997157523517
        },
        {
          "lat": -34.5693489037078,
          "lng": -58.4001266601711
        },
        {
          "lat": -34.5721906912083,
          "lng": -58.3952057970513
        }
      ]
    ]
  },
  {
    "name": "Retiro",
    "coords": [
      [
        {
          "lat": -34.5787043103248,
          "lng": -58.3742728981345
        },
        {
          "lat": -34.5782106787894,
          "lng": -58.3679284958736
        },
        {
          "lat": -34.5797048655816,
          "lng": -58.3653152245902
        },
        {
          "lat": -34.5801507722698,
          "lng": -58.365245643362
        },
        {
          "lat": -34.5808300747436,
          "lng": -58.3705580715031
        },
        {
          "lat": -34.5817286249004,
          "lng": -58.3689696460942
        },
        {
          "lat": -34.5812273154272,
          "lng": -58.3626322331095
        },
        {
          "lat": -34.5824233795893,
          "lng": -58.3605253631374
        },
        {
          "lat": -34.5828695601576,
          "lng": -58.3604763381045
        },
        {
          "lat": -34.5835660432785,
          "lng": -58.3661401151341
        },
        {
          "lat": -34.5844993315595,
          "lng": -58.3649407304481
        },
        {
          "lat": -34.5841450577936,
          "lng": -58.3598967036561
        },
        {
          "lat": -34.5859313453833,
          "lng": -58.3597417369954
        },
        {
          "lat": -34.5862668424668,
          "lng": -58.3636567169966
        },
        {
          "lat": -34.5874910086758,
          "lng": -58.3634970230128
        },
        {
          "lat": -34.5871906186234,
          "lng": -58.3595841512016
        },
        {
          "lat": -34.588296270335,
          "lng": -58.3597182157167
        },
        {
          "lat": -34.5885522051086,
          "lng": -58.3608324441504
        },
        {
          "lat": -34.588936020727,
          "lng": -58.3607402351315
        },
        {
          "lat": -34.5885638625568,
          "lng": -58.36088858366
        },
        {
          "lat": -34.5900082744266,
          "lng": -58.3679912957437
        },
        {
          "lat": -34.5904434992359,
          "lng": -58.3679314596311
        },
        {
          "lat": -34.5909712317189,
          "lng": -58.3665190169642
        },
        {
          "lat": -34.594273385455,
          "lng": -58.3643573602582
        },
        {
          "lat": -34.5944654129146,
          "lng": -58.364833021963
        },
        {
          "lat": -34.5928245998606,
          "lng": -58.3659451327298
        },
        {
          "lat": -34.5941505179534,
          "lng": -58.3690536114633
        },
        {
          "lat": -34.5975208921517,
          "lng": -58.3678871102317
        },
        {
          "lat": -34.5974312639569,
          "lng": -58.366499858982
        },
        {
          "lat": -34.5980395042448,
          "lng": -58.366109349811
        },
        {
          "lat": -34.5973982605621,
          "lng": -58.366138363271
        },
        {
          "lat": -34.5972100033554,
          "lng": -58.3638252569407
        },
        {
          "lat": -34.5955045617149,
          "lng": -58.3644047575726
        },
        {
          "lat": -34.5953112465266,
          "lng": -58.3640988623279
        },
        {
          "lat": -34.596659359029,
          "lng": -58.3634159790862
        },
        {
          "lat": -34.5955167863613,
          "lng": -58.3603802601795
        },
        {
          "lat": -34.5949935862931,
          "lng": -58.3600553480135
        },
        {
          "lat": -34.5946881997761,
          "lng": -58.3542612504891
        },
        {
          "lat": -34.5953566479576,
          "lng": -58.3511383195086
        },
        {
          "lat": -34.5948573510851,
          "lng": -58.3542795087346
        },
        {
          "lat": -34.5952442785373,
          "lng": -58.3592514963297
        },
        {
          "lat": -34.5971255666786,
          "lng": -58.3634459577139
        },
        {
          "lat": -34.5980614176257,
          "lng": -58.3632336427926
        },
        {
          "lat": -34.5981362266419,
          "lng": -58.3638616554643
        },
        {
          "lat": -34.5992928735805,
          "lng": -58.3868634379837
        },
        {
          "lat": -34.5916482473693,
          "lng": -58.3879499543075
        },
        {
          "lat": -34.5875003435414,
          "lng": -58.3836858955457
        },
        {
          "lat": -34.5835513995301,
          "lng": -58.3869635729226
        },
        {
          "lat": -34.5808309894752,
          "lng": -58.3916446426145
        },
        {
          "lat": -34.5782016523951,
          "lng": -58.389864551892
        },
        {
          "lat": -34.5782352961729,
          "lng": -58.3835712371255
        },
        {
          "lat": -34.5801619115881,
          "lng": -58.3798362674721
        },
        {
          "lat": -34.5799504792293,
          "lng": -58.3761600512028
        },
        {
          "lat": -34.5805200713283,
          "lng": -58.3751214877465
        },
        {
          "lat": -34.5791023036155,
          "lng": -58.3739717230009
        },
        {
          "lat": -34.5775452603952,
          "lng": -58.3767109137284
        },
        {
          "lat": -34.5774840705932,
          "lng": -58.3760409692424
        },
        {
          "lat": -34.5787043103248,
          "lng": -58.3742728981345
        }
      ]
    ]
  },
  {
    "name": "Núñez",
    "coords": [
      [
        {
          "lat": -34.5275529914205,
          "lng": -58.4566549786532
        },
        {
          "lat": -34.5279131056002,
          "lng": -58.4559431274602
        },
        {
          "lat": -34.5286691819932,
          "lng": -58.4559142466251
        },
        {
          "lat": -34.5298839698608,
          "lng": -58.454071282383
        },
        {
          "lat": -34.5313403396775,
          "lng": -58.4535623166767
        },
        {
          "lat": -34.5330768334737,
          "lng": -58.455697734314
        },
        {
          "lat": -34.5352138304699,
          "lng": -58.4549164980779
        },
        {
          "lat": -34.5377987902741,
          "lng": -58.4594426423642
        },
        {
          "lat": -34.5426523436413,
          "lng": -58.4492746382907
        },
        {
          "lat": -34.5489847697112,
          "lng": -58.4541211632346
        },
        {
          "lat": -34.5505040530708,
          "lng": -58.4530063043606
        },
        {
          "lat": -34.558928524183,
          "lng": -58.4691841950682
        },
        {
          "lat": -34.5524209338867,
          "lng": -58.4744359204902
        },
        {
          "lat": -34.5489400157911,
          "lng": -58.468189262655
        },
        {
          "lat": -34.5386305921147,
          "lng": -58.4759530989691
        },
        {
          "lat": -34.5332608869246,
          "lng": -58.4637955967509
        },
        {
          "lat": -34.5276200759232,
          "lng": -58.4588930868133
        },
        {
          "lat": -34.5275529914205,
          "lng": -58.4566549786532
        }
      ]
    ]
  },
  {
    "name": "La Boca",
    "coords": [
      [
        {
          "lat": -34.6194307028365,
          "lng": -58.3552004576535
        },
        {
          "lat": -34.6197709409727,
          "lng": -58.3526924458975
        },
        {
          "lat": -34.6191674154407,
          "lng": -58.3515200778185
        },
        {
          "lat": -34.6197903347382,
          "lng": -58.3495720908321
        },
        {
          "lat": -34.6189652424629,
          "lng": -58.3478479591372
        },
        {
          "lat": -34.6189999297413,
          "lng": -58.3445916669237
        },
        {
          "lat": -34.619629943859,
          "lng": -58.3446669733515
        },
        {
          "lat": -34.6198362253202,
          "lng": -58.3451848409669
        },
        {
          "lat": -34.6192115747039,
          "lng": -58.3463236325019
        },
        {
          "lat": -34.6199892889332,
          "lng": -58.3471505880733
        },
        {
          "lat": -34.6229555756402,
          "lng": -58.345932347317
        },
        {
          "lat": -34.6220084024104,
          "lng": -58.3460919253581
        },
        {
          "lat": -34.6215186055199,
          "lng": -58.3454815647658
        },
        {
          "lat": -34.621340985043,
          "lng": -58.344703633036
        },
        {
          "lat": -34.6217586862411,
          "lng": -58.3440572366706
        },
        {
          "lat": -34.6194896055236,
          "lng": -58.3440467277246
        },
        {
          "lat": -34.6185678614715,
          "lng": -58.3428547516694
        },
        {
          "lat": -34.6186646163189,
          "lng": -58.3388651537555
        },
        {
          "lat": -34.6191238325347,
          "lng": -58.3381969094655
        },
        {
          "lat": -34.6216352521155,
          "lng": -58.3371615945022
        },
        {
          "lat": -34.6227637351371,
          "lng": -58.3373250427619
        },
        {
          "lat": -34.622852448013,
          "lng": -58.3416721854743
        },
        {
          "lat": -34.6222385019308,
          "lng": -58.3420786575974
        },
        {
          "lat": -34.6226810019947,
          "lng": -58.3430644075687
        },
        {
          "lat": -34.6237087714346,
          "lng": -58.3422429740729
        },
        {
          "lat": -34.6231435665641,
          "lng": -58.3418820048572
        },
        {
          "lat": -34.6231366533583,
          "lng": -58.3406675330179
        },
        {
          "lat": -34.6246630377835,
          "lng": -58.3384873199659
        },
        {
          "lat": -34.6248470149282,
          "lng": -58.3370402367563
        },
        {
          "lat": -34.6264528532951,
          "lng": -58.3351440325011
        },
        {
          "lat": -34.6271231364708,
          "lng": -58.3351430067125
        },
        {
          "lat": -34.6281969140175,
          "lng": -58.3361927168213
        },
        {
          "lat": -34.6289213562468,
          "lng": -58.3388637688002
        },
        {
          "lat": -34.6278425687505,
          "lng": -58.3397320263934
        },
        {
          "lat": -34.6278282431047,
          "lng": -58.3406448004275
        },
        {
          "lat": -34.6261838466743,
          "lng": -58.342432726863
        },
        {
          "lat": -34.6263914188413,
          "lng": -58.344273269061
        },
        {
          "lat": -34.6285811173435,
          "lng": -58.3415656794305
        },
        {
          "lat": -34.6289594601415,
          "lng": -58.3413899519558
        },
        {
          "lat": -34.6294889469442,
          "lng": -58.3424863504593
        },
        {
          "lat": -34.6280150178492,
          "lng": -58.3445721407013
        },
        {
          "lat": -34.628373631715,
          "lng": -58.3450049620233
        },
        {
          "lat": -34.6271921872537,
          "lng": -58.3464491476757
        },
        {
          "lat": -34.6274057802957,
          "lng": -58.3467009498596
        },
        {
          "lat": -34.6286697366002,
          "lng": -58.3453666384515
        },
        {
          "lat": -34.6272820677151,
          "lng": -58.347049260788
        },
        {
          "lat": -34.6290838322825,
          "lng": -58.3487836817
        },
        {
          "lat": -34.6299375168546,
          "lng": -58.3479606945131
        },
        {
          "lat": -34.6302868425371,
          "lng": -58.3482980330144
        },
        {
          "lat": -34.6311665900514,
          "lng": -58.3479210322604
        },
        {
          "lat": -34.6309017359166,
          "lng": -58.3476569510739
        },
        {
          "lat": -34.6313934740337,
          "lng": -58.3475692823332
        },
        {
          "lat": -34.6316595572898,
          "lng": -58.3460970492321
        },
        {
          "lat": -34.6321183153882,
          "lng": -58.3477459113047
        },
        {
          "lat": -34.6326155692265,
          "lng": -58.347696329214
        },
        {
          "lat": -34.6325734820828,
          "lng": -58.3490379087601
        },
        {
          "lat": -34.6323485736997,
          "lng": -58.3501161040274
        },
        {
          "lat": -34.6313557842819,
          "lng": -58.3511383259319
        },
        {
          "lat": -34.6292818647747,
          "lng": -58.3518509790422
        },
        {
          "lat": -34.629161718883,
          "lng": -58.3529881280329
        },
        {
          "lat": -34.6239134427259,
          "lng": -58.3605134042249
        },
        {
          "lat": -34.6242537235382,
          "lng": -58.3608920836947
        },
        {
          "lat": -34.6236887378709,
          "lng": -58.3617339711407
        },
        {
          "lat": -34.6243937126303,
          "lng": -58.3610186943033
        },
        {
          "lat": -34.6246846438861,
          "lng": -58.3612622680202
        },
        {
          "lat": -34.6291112900379,
          "lng": -58.3547708335693
        },
        {
          "lat": -34.6335819181831,
          "lng": -58.3527538873144
        },
        {
          "lat": -34.6365300376758,
          "lng": -58.3541310741834
        },
        {
          "lat": -34.6385879069135,
          "lng": -58.3569385928756
        },
        {
          "lat": -34.6392269421011,
          "lng": -58.3580225540775
        },
        {
          "lat": -34.639419295966,
          "lng": -58.3611105807672
        },
        {
          "lat": -34.639893055841,
          "lng": -58.3614226418163
        },
        {
          "lat": -34.6407228515301,
          "lng": -58.3609028220366
        },
        {
          "lat": -34.6418688232983,
          "lng": -58.3581253269021
        },
        {
          "lat": -34.6440442838123,
          "lng": -58.3573173309192
        },
        {
          "lat": -34.6449824366478,
          "lng": -58.3575905964166
        },
        {
          "lat": -34.6459828754798,
          "lng": -58.3597966640049
        },
        {
          "lat": -34.6479447916213,
          "lng": -58.3617087246169
        },
        {
          "lat": -34.6483201404589,
          "lng": -58.3643480882644
        },
        {
          "lat": -34.6501366170196,
          "lng": -58.3676488363194
        },
        {
          "lat": -34.6294937856849,
          "lng": -58.3706581576618
        },
        {
          "lat": -34.6271424047803,
          "lng": -58.3679451333274
        },
        {
          "lat": -34.6251954580434,
          "lng": -58.3679712009248
        },
        {
          "lat": -34.6251395732768,
          "lng": -58.3631158163979
        },
        {
          "lat": -34.6176387636499,
          "lng": -58.3559976557415
        },
        {
          "lat": -34.6194307028365,
          "lng": -58.3552004576535
        }
      ]
    ]
  }
]